setup.py
ElasticSearchLib/ElasticSearchLib.py
ElasticSearchLib/__init__.py
robotframework_elasticsearch.egg-info/PKG-INFO
robotframework_elasticsearch.egg-info/SOURCES.txt
robotframework_elasticsearch.egg-info/dependency_links.txt
robotframework_elasticsearch.egg-info/requires.txt
robotframework_elasticsearch.egg-info/top_level.txt