Metadata-Version: 1.0
Name: robotframework-elasticsearch
Version: 1.1
Summary: ElasticSearch library for Robot Framework
Home-page: https://github.com/pagesjaunes/robotframework-elasticsearch
Author: PagesJaunes
Author-email: fdepaulis@pagesjaunes.fr
License: UNKNOWN
Platform: UNKNOWN
